{
  "name": "Viviane de Vries",
  "profession": "Ostéopathe Exclusif",
  "logo": "images/logo.png",
  "stamp": "images/stamp.png",
  "addressLines": [
    "Cabinet « Villa DREAM »",
    "156 chemin de la Batterie",
    "97126 DESHAIES"
  ],
  "phone": "06.20.76.70.80",
  "siret": "53900011700041",
  "rpps": "10010075736",
  "services": [
    { "label": "Séance d'ostéopathie (45min)", "price": 70 },
    { "label": "Massage bien-être (60min)", "price": 70 },
    { "label": "Massage bien-être (90min)", "price": 90 },
    { "label": "Pack gommage + massage", "price": 100 }
  ]
}